lambchop/__init__.py
lambchop/cli.py
lambchop/client.py
lambchop/datastructures.py
lambchop/exceptions.py
lambchop/server.py
lambchop/sidekick.py
lambchop/utils.py
lambchop-0.0.4.dist-info/LICENSE
lambchop-0.0.4.dist-info/METADATA
lambchop-0.0.4.dist-info/WHEEL
lambchop-0.0.4.dist-info/entry_points.txt
lambchop-0.0.4.dist-info/top_level.txt
lambchop-0.0.4.dist-info/RECORD
