Metadata-Version: 2.1
Name: lambchop
Version: 0.0.4
Summary: My package description
Author: bohemdev
License: The MIT License (MIT)
Classifier: License :: OSI Approved :: MIT License
License-File: LICENSE
Requires-Dist: anyio
Requires-Dist: dill
Requires-Dist: typer[all]
Provides-Extra: cli
Requires-Dist: typer[all] ; extra == 'cli'
